<annotation>
    <folder>images</folder>
    <filename>frame3.jpg</filename>
    <size>
        <width>512</width>
        <height>512</height>
        <depth>3</depth>
    </size>
    <segmented>0</segmented>
    <object>
        <name>shark</name>
        <pose>Unspecified</pose>
        <truncated>0</truncated>
        <occluded>0</occluded>
        <difficult>0</difficult>
        <bndbox>
            <xmin>125</xmin>
            <ymin>53</ymin>
            <xmax>234</xmax>
            <ymax>324</ymax>
        </bndbox>
    </object>
</annotation>